{
  "type": "EFFECT_REQUESTED",
  "recordedAt": "2026-03-29T16:57:06.942Z",
  "data": {
    "effectId": "01KMX8E7JM3DPNSYWKXZ11HRWD",
    "invocationKey": "easyssh-iterative-refactor:S000034:easyssh-refactor-step",
    "invocationHash": "b2367305e3d1071806d52d1c416947cc47601c97a573525a73e6bc4092937619",
    "stepId": "S000034",
    "taskId": "easyssh-refactor-step",
    "kind": "agent",
    "label": "EasySSH refactor step 34",
    "taskDefRef": "tasks/01KMX8E7JM3DPNSYWKXZ11HRWD/task.json"
  },
  "checksum": "7445522cf52d03b5b38ff8acedfa89644b47aa046449e9dee9a56e4863ce3d59"
}
